psychopath/__init__.py
psychopath/__version__.py
psychopath/constants.py
psychopath/helpers.py
psychopath/main.py
psychopath-0.0.0.dist-info/LICENSE
psychopath-0.0.0.dist-info/METADATA
psychopath-0.0.0.dist-info/WHEEL
psychopath-0.0.0.dist-info/top_level.txt
psychopath-0.0.0.dist-info/RECORD
